alt_profanity_check-1.7.2.dist-info/licenses/LICENSE
profanity_check/__init__.py
profanity_check/command_line.py
profanity_check/profanity_check.py
profanity_check/data/model.joblib
profanity_check/data/vectorizer.joblib
alt_profanity_check-1.7.2.dist-info/METADATA
alt_profanity_check-1.7.2.dist-info/WHEEL
alt_profanity_check-1.7.2.dist-info/entry_points.txt
alt_profanity_check-1.7.2.dist-info/top_level.txt
alt_profanity_check-1.7.2.dist-info/RECORD
